slack_watchman_eg/__init__.py
slack_watchman_eg/__main__.py
slack_watchman_eg/__version__.py
slack_watchman_eg/signature_updater.py
slack_watchman_eg/slack_wrapper.py
slack_watchman_eg/sw_logger.py
slack_watchman_eg/models/__init__.py
slack_watchman_eg/models/conversation.py
slack_watchman_eg/models/enterprise.py
slack_watchman_eg/models/post.py
slack_watchman_eg/models/signature.py
slack_watchman_eg/models/user.py
slack_watchman_eg/models/workspace.py
slack_watchman_eg-2.0.0.dist-info/LICENSE
slack_watchman_eg-2.0.0.dist-info/METADATA
slack_watchman_eg-2.0.0.dist-info/WHEEL
slack_watchman_eg-2.0.0.dist-info/entry_points.txt
slack_watchman_eg-2.0.0.dist-info/top_level.txt
slack_watchman_eg-2.0.0.dist-info/RECORD
