Metadata-Version: 2.1
Name: slack-watchman-eg
Version: 2.0.0
Summary: Monitoring Slack Enterprise Grid for exposed secrets
Home-page: https://github.com/PaperMtn/slack-watchman-enterprise-grid
Author: PaperMtn
Author-email: papermtn@protonmail.com
License: GPL-3.0
Keywords: audit,slack,slack-watchman,watchman,blue-team,red-team,threat-hunting,slack-watchman-enterprise-grid
Classifier: Intended Audience :: Information Technology
Classifier: Topic :: Security
Classifier: License :: OSI Approved :: GNU General Public License v3 (GPLv3)
Classifier: Programming Language :: Python :: 3.10
Requires-Python: >=3.10
License-File: LICENSE
Requires-Dist: requests
Requires-Dist: PyYAML
Requires-Dist: numpy
Requires-Dist: colorama
